{
  "schemaVersion": 1,
  "id": "smallrod",
  "version": "${version}",
  "name": "SmallRod",
  "description": "",
  "authors": ["AntiCore"],
  "contact": {},
  "license": "All-Rights-Reserved",
  "environment": "client",
  "entrypoints": {
    "client": [
      "org.burcope.smallrod.client.SmallrodClient"
    ],
    "main": [
      "org.burcope.smallrod.Smallrod"
    ]
  },
  "mixins": [
    "smallrod.mixins.json"
  ],
  "depends": {
    "fabricloader": ">=${loader_version}",
    "fabric": "*",
    "minecraft": "${minecraft_version}"
  }
}
